pixeo/__init__.py
pixeo/drivce/__init__.py
pixeo/drivce/device.py
pixeo/drivce/device_manager.py
pixeo/log/__init__.py
pixeo/log/log.py
pixeo/resource/__init__.py
pixeo/resource/button.py
pixeo/resource/page.py
pixeo/resource/resource.py
pixeo/task/__init__.py
pixeo/task/task.py
pixeo-1.0.0.dist-info/METADATA
pixeo-1.0.0.dist-info/WHEEL
pixeo-1.0.0.dist-info/top_level.txt
pixeo-1.0.0.dist-info/RECORD
